lora_calc/__init__.py
lora_calc/lora_utils.py
lora_calc-0.1.1.dist-info/METADATA
lora_calc-0.1.1.dist-info/WHEEL
lora_calc-0.1.1.dist-info/RECORD
