Metadata-Version: 2.3
Name: lora-calc
Version: 0.1.1
Summary: 
Author: coleandreoli
Author-email: coleandreoli@gmail.com
Requires-Python: >=3.12
Classifier: Programming Language :: Python :: 3
Classifier: Programming Language :: Python :: 3.12
Classifier: Programming Language :: Python :: 3.13
